SqDetect_101/seq_detect.v
module seq_detect(
	input			clk,
	input			reset,
	input			x_in,
	output logic	z_out
);

	logic[1:0] state, next_state;

	parameter S0 = 2'b00, S1 = 2'b01, S2 = 2'b10;

	always@(x_in or state)begin
		case(state)
			S0: if(x_in == 1)begin
					next_state = S1;
					z_out = 0;
				end
				else begin
					next_state = S0;
					z_out = 0;
				end
			S1: if(x_in == 0)begin
					next_state = S2;
					z_out = 0;
				end
				else begin
					next_state = S1;
					z_out = 0;
				end
			S2: if(x_in == 1)begin
					next_state = S1;
					z_out = 1;
				end
				else begin
					next_state = S0;
					z_out = 0;
				end
		endcase
	end

	always@(posedge clk)begin
		if(reset)begin
			state <= S0;
		end
		else begin
			state <= next_state;
		end
	end
endmodule

SqDetect_101/seq_detect_tb.v
module seq_detect_tb();
	logic clk, reset, x_in;
	wire z_out;

	seq_detect seq_1(
		.clk(clk),
		.reset(reset),
		.x_in(x_in),
		.z_out(z_out)
	);

	initial begin
		reset 	= 1;
		clk 	= 0;
		x_in 	= 0;

		#10 reset 	= 0;
		#10 x_in	= 0;
		#10 x_in 	= 1;
		#10 x_in 	= 1;
		#10 x_in 	= 0;
		#10 x_in 	= 1;
		#10 x_in 	= 1;
		#10 x_in 	= 0;
		#10 x_in 	= 1;
		#10 x_in 	= 0;
		#10 x_in 	= 1;
		#10 x_in 	= 0;
		#10 $finish;
	end

	always begin
		#5 clk = ~clk;
	end

	// dump wave
	initial begin
		$dumpfile("wave.vcd");
		$dumpvars(0,seq_detect_tb);
	end
endmodule

SqDetect_101/wave.vcd
$date
	Tue Aug 07 01:28:42 2018
$end
$version
	Icarus Verilog
$end
$timescale
	1s
$end
$scope module seq_detect_tb $end
$var wire 1 ! z_out $end
$var reg 1 " clk $end
$var reg 1 # reset $end
$var reg 1 $ x_in $end
$scope module seq_1 $end
$var wire 1 " clk $end
$var wire 1 # reset $end
$var wire 1 $ x_in $end
$var reg 2 % next_state [1:0] $end
$var reg 2 & state [1:0] $end
$var reg 1 ! z_out $end
$upscope $end
$upscope $end
$enddefinitions $end
#0
$dumpvars
bx &
bx %
0$
1#
0"
x!
$end
#5
0!
b0 %
b0 &
1"
#10
0"
0#
#15
1"
#20
0"
#25
1"
#30
b1 %
0"
1$
#35
b1 &
1"
#40
0"
#45
1"
#50
b10 %
0"
0$
#55
b0 %
b10 &
1"
#60
1!
b1 %
0"
1$
#65
0!
b1 &
1"
#70
0"
#75
1"
#80
b10 %
0"
0$
#85
b0 %
b10 &
1"
#90
1!
b1 %
0"
1$
#95
0!
b1 &
1"
#100
b10 %
0"
0$
#105
b0 %
b10 &
1"
#110
1!
b1 %
0"
1$
#115
0!
b1 &
1"
#120
b10 %
0"
0$
#125
b0 %
b10 &
1"
