freq_div_odd/freq_div_odd.v
/*Frequency Divider by Any Odd Number N*/

`timescale 1ns/1ns

module freq_div_odd(
	input			clk_in,
	input			reset,
	output logic	clk_out
);
	parameter N = 9;
	logic					clk1_out, clk2_out, next_clk1_out, next_clk2_out;
	logic[$clog2(N)+1:0]	pos_count, neg_count, next_pos_count, next_neg_count;
	
	always@(pos_count)begin
		next_pos_count	= (pos_count == (N-1)) ? 0 : pos_count + 1;
		
		if(pos_count == (N-1))begin
			next_clk1_out = 1;
		end
		else if(pos_count == (N-1)/2 - 1)begin
			next_clk1_out = 0;
		end
	end
	
	always@(neg_count)begin
		next_neg_count	= (neg_count == (N-1)) ? 0 : neg_count + 1;
		
		if(neg_count == (N-1))begin
			next_clk2_out = 1;
		end
		else if(neg_count == (N-1)/2 - 1)begin
			next_clk2_out = 0;
		end
	end

	always@(pos_count or neg_count)begin
		clk_out = clk1_out || clk2_out;
	end

	always@(posedge clk_in)begin
		if(reset)begin
			clk1_out	<= 1'b0;
			pos_count	<= 0;
		end
		else begin
			pos_count	<= next_pos_count;
			clk1_out	<= next_clk1_out;
		end
	end
	
	always@(negedge clk_in)begin
		if(reset)begin
			clk2_out	<= 1'b0;
			neg_count	<= 0;
		end
		else begin
			neg_count	<= next_neg_count;
			clk2_out	<= next_clk2_out;
		end
	end
endmodule

freq_div_odd/freq_div_odd_tb.v
module freq_div_odd_tb();
	logic clk_in, reset;
	wire clk_out;

	freq_div_odd div_odd(
		.clk_in(clk_in),
		.reset(reset),
		.clk_out(clk_out)
	);

	initial begin
		clk_in 	= 0;
		reset	= 1;

		#10
		reset	= 0;

	//	#50
	//	reset	= 1;
	//	#60
	//	reset	= 0;

		#400 $finish;
	end

	always begin
		#5 clk_in = ~clk_in;
	end

	initial begin
	$dumpfile("wave.vcd");
	$dumpvars(0,freq_div_odd_tb);
	end
endmodule

freq_div_odd/wave.vcd
$date
	Tue Aug 14 00:13:38 2018
$end
$version
	Icarus Verilog
$end
$timescale
	1ns
$end
$scope module freq_div_odd_tb $end
$var wire 1 ! clk_out $end
$var reg 1 " clk_in $end
$var reg 1 # reset $end
$scope module div_odd $end
$var wire 1 " clk_in $end
$var wire 1 # reset $end
$var reg 1 $ clk1_out $end
$var reg 1 % clk2_out $end
$var reg 1 ! clk_out $end
$var reg 6 & neg_count [5:0] $end
$var reg 1 ' next_clk1_out $end
$var reg 1 ( next_clk2_out $end
$var reg 6 ) next_neg_count [5:0] $end
$var reg 6 * next_pos_count [5:0] $end
$var reg 6 + pos_count [5:0] $end
$upscope $end
$upscope $end
$enddefinitions $end
#0
$dumpvars
bx +
bx *
b1 )
x(
x'
b0 &
0%
x$
1#
0"
x!
$end
#5
0!
b1 *
b0 +
0$
1"
#10
x!
b10 )
x%
b1 &
0"
0#
#15
b10 *
x$
b1 +
1"
#20
b11 )
b10 &
0"
#25
b11 *
b10 +
1"
#30
0(
b100 )
b11 &
0"
#35
0'
b100 *
b11 +
1"
#40
b101 )
0%
b100 &
0"
#45
0!
b101 *
0$
b100 +
1"
#50
b110 )
b101 &
0"
#55
b110 *
b101 +
1"
#60
b111 )
b110 &
0"
#65
b111 *
b110 +
1"
#70
b1000 )
b111 &
0"
#75
b1000 *
b111 +
1"
#80
1(
b0 )
b1000 &
0"
#85
1'
b0 *
b1000 +
1"
#90
1!
b1 )
1%
b0 &
0"
#95
b1 *
1$
b0 +
1"
#100
b10 )
b1 &
0"
#105
b10 *
b1 +
1"
#110
b11 )
b10 &
0"
#115
b11 *
b10 +
1"
#120
0(
b100 )
b11 &
0"
#125
0'
b100 *
b11 +
1"
#130
b101 )
0%
b100 &
0"
#135
0!
b101 *
0$
b100 +
1"
#140
b110 )
b101 &
0"
#145
b110 *
b101 +
1"
#150
b111 )
b110 &
0"
#155
b111 *
b110 +
1"
#160
b1000 )
b111 &
0"
#165
b1000 *
b111 +
1"
#170
1(
b0 )
b1000 &
0"
#175
1'
b0 *
b1000 +
1"
#180
1!
b1 )
1%
b0 &
0"
#185
b1 *
1$
b0 +
1"
#190
b10 )
b1 &
0"
#195
b10 *
b1 +
1"
#200
b11 )
b10 &
0"
#205
b11 *
b10 +
1"
#210
0(
b100 )
b11 &
0"
#215
0'
b100 *
b11 +
1"
#220
b101 )
0%
b100 &
0"
#225
0!
b101 *
0$
b100 +
1"
#230
b110 )
b101 &
0"
#235
b110 *
b101 +
1"
#240
b111 )
b110 &
0"
#245
b111 *
b110 +
1"
#250
b1000 )
b111 &
0"
#255
b1000 *
b111 +
1"
#260
1(
b0 )
b1000 &
0"
#265
1'
b0 *
b1000 +
1"
#270
1!
b1 )
1%
b0 &
0"
#275
b1 *
1$
b0 +
1"
#280
b10 )
b1 &
0"
#285
b10 *
b1 +
1"
#290
b11 )
b10 &
0"
#295
b11 *
b10 +
1"
#300
0(
b100 )
b11 &
0"
#305
0'
b100 *
b11 +
1"
#310
b101 )
0%
b100 &
0"
#315
0!
b101 *
0$
b100 +
1"
#320
b110 )
b101 &
0"
#325
b110 *
b101 +
1"
#330
b111 )
b110 &
0"
#335
b111 *
b110 +
1"
#340
b1000 )
b111 &
0"
#345
b1000 *
b111 +
1"
#350
1(
b0 )
b1000 &
0"
#355
1'
b0 *
b1000 +
1"
#360
1!
b1 )
1%
b0 &
0"
#365
b1 *
1$
b0 +
1"
#370
b10 )
b1 &
0"
#375
b10 *
b1 +
1"
#380
b11 )
b10 &
0"
#385
b11 *
b10 +
1"
#390
0(
b100 )
b11 &
0"
#395
0'
b100 *
b11 +
1"
#400
b101 )
0%
b100 &
0"
#405
0!
b101 *
0$
b100 +
1"
#410
b110 )
b101 &
0"
