freq_div2/freq_div2.v
`timescale 1ns/1ns

module freq_div2(
	input			clk_100,
	output 			clk_out
);   

	parameter N	 = 4'd8;
	reg[3:0] cnt = 4'd0;
	
	always@(posedge clk_100)
	begin
	    if(cnt == (N-1))
	       cnt <= 4'd0;
	    else
	       cnt <= cnt + 1'b1;
	end
	
	reg clkout =1'b0;
	always@(posedge clk_100)
	begin
	  if(cnt == 4'd0)
	    clkout <= 1'b1;
	  else if(cnt == (N/2))
	    clkout <= 1'b0;
	  else
	    clkout <= clkout;
	end
	assign clk_out =clkout;
endmodule

freq_div2/freq_div2_tb.v
module freq_div2_tb();
	logic clk_in;
	wire clk_out;

	freq_div2 div2(
		.clk_100(clk_in),
		.clk_out(clk_out)
	);

	initial begin
		clk_in 	= 0;
		#100 $finish;
	end

	always begin
		#5 clk_in = ~clk_in;
	end

	initial begin
	$dumpfile("wave.vcd");
	$dumpvars(0,freq_div2_tb);
	end
endmodule

freq_div2/wave.vcd
$date
	Thu Aug 09 01:01:26 2018
$end
$version
	Icarus Verilog
$end
$timescale
	1ns
$end
$scope module freq_div2_tb $end
$var wire 1 ! clk_out $end
$var reg 1 " clk_in $end
$scope module div2 $end
$var wire 1 " clk_100 $end
$var wire 1 ! clk_out $end
$var reg 1 # clkout $end
$var reg 4 $ cnt [3:0] $end
$upscope $end
$upscope $end
$enddefinitions $end
#0
$dumpvars
b0 $
0#
0"
0!
$end
#5
b1 $
1!
1#
1"
#10
0"
#15
b10 $
1"
#20
0"
#25
b11 $
1"
#30
0"
#35
b100 $
1"
#40
0"
#45
b101 $
0!
0#
1"
#50
0"
#55
b110 $
1"
#60
0"
#65
b111 $
1"
#70
0"
#75
b0 $
1"
#80
0"
#85
b1 $
1!
1#
1"
#90
0"
#95
b10 $
1"
